novel_genie/__init__.py
novel_genie/app.py
novel_genie/config.py
novel_genie/cost.py
novel_genie/exceptions.py
novel_genie/generate_novel.py
novel_genie/llm.py
novel_genie/logger.py
novel_genie/schema.py
novel_genie/utils.py
novel_genie-0.1.0.dist-info/METADATA
novel_genie-0.1.0.dist-info/WHEEL
novel_genie-0.1.0.dist-info/entry_points.txt
novel_genie-0.1.0.dist-info/top_level.txt
novel_genie-0.1.0.dist-info/RECORD
