Metadata-Version: 2.1
Name: novel-genie
Version: 0.1.0
Summary: A tool to generate novels via command line input or screenshots
Home-page: https://github.com/mannaandpoem/NovelGenie
Author: mannaandpoem
Author-email: 1580466765@qq.com
Classifier: Programming Language :: Python :: 3
Classifier: Operating System :: OS Independent
Requires-Python: >=3.10
Requires-Dist: openai~=0.28.0
Requires-Dist: pyyaml~=6.0.2
Requires-Dist: pydantic~=2.10.2
Requires-Dist: loguru~=0.7.2
Requires-Dist: easyocr~=1.7.2
Requires-Dist: pyautogui~=0.9.54
Requires-Dist: pynput~=1.7.7
Requires-Dist: Pillow~=11.0.0
